[
  {
    "id": "qr",
    "text": "Need a free QR code? Try FreeFastQR!",
    "href": "https://freefastqr.com",
    "color": "#1978e5",
    "excludeOn": ["freefastqr.com"]
  },
  {
    "id": "password",
    "text": "Generate strong passwords at FreeFastPassword.",
    "href": "https://freefastpassword.com",
    "color": "#1978e5",
    "excludeOn": ["freefastpassword.com"]
  },
  {
    "id": "pomo",
    "text": "Boost focus with our free Pomodoro Timer",
    "href": "",
    "color": "#ff6b6b",
    "excludeOn": ["pomodorotimerfree.com"]
  }
]
